hybridbackend_tf115_cu114.libs/libtasn1-f32a1ca1.so.6.5.5
hybridbackend_tf115_cu114.libs/liblber-2-03a6a3d3.4.so.2.10.8
hybridbackend_tf115_cu114.libs/libnghttp2-e4f1953a.so.14.15.2
hybridbackend_tf115_cu114.libs/libnvToolsExt-847d78f2.so.1.0.0
hybridbackend_tf115_cu114.libs/libasn1-4e058a8a.so.8.0.0
hybridbackend_tf115_cu114.libs/libnettle-80a178a8.so.6.5
hybridbackend_tf115_cu114.libs/libsasl2-991d3009.so.2.0.25
hybridbackend_tf115_cu114.libs/libk5crypto-483d4c1b.so.3.1
hybridbackend_tf115_cu114.libs/libidn2-e8ca7a45.so.0.3.3
hybridbackend_tf115_cu114.libs/libwind-eb20aae7.so.0.0.0
hybridbackend_tf115_cu114.libs/libcrypto-92aa3375.so.1.1
hybridbackend_tf115_cu114.libs/libcom_err-be6c2b59.so.2.1
hybridbackend_tf115_cu114.libs/libkeyutils-ea5bf3d6.so.1.5
hybridbackend_tf115_cu114.libs/libgnutls-2a7b15c2.so.30.14.10
hybridbackend_tf115_cu114.libs/libcudart-f9a9d13a.so.11.4.108
hybridbackend_tf115_cu114.libs/libroken-62f5234d.so.18.1.0
hybridbackend_tf115_cu114.libs/libhogweed-98deba4e.so.4.5
hybridbackend_tf115_cu114.libs/libgssapi-61ee414b.so.3.0.0
hybridbackend_tf115_cu114.libs/libgssapi_krb5-b9f83a34.so.2.2
hybridbackend_tf115_cu114.libs/libpsl-6b155035.so.5.2.0
hybridbackend_tf115_cu114.libs/libgmp-0afb61ed.so.10.3.2
hybridbackend_tf115_cu114.libs/libp11-kit-8ba9ed41.so.0.3.0
hybridbackend_tf115_cu114.libs/libcurl-3e9fb682.so.4.5.0
hybridbackend_tf115_cu114.libs/libldap_r-2-ac1284a4.4.so.2.10.8
hybridbackend_tf115_cu114.libs/librtmp-a6d10317.so.1
hybridbackend_tf115_cu114.libs/libssl-e86845de.so.1.1
hybridbackend_tf115_cu114.libs/libheimbase-b668efee.so.1.0.0
hybridbackend_tf115_cu114.libs/libkrb5-6e6fd495.so.26.0.0
hybridbackend_tf115_cu114.libs/libsqlite3-77a38299.so.0.8.6
hybridbackend_tf115_cu114.libs/libkrb5support-94962fff.so.0.1
hybridbackend_tf115_cu114.libs/libffi-5a675e4f.so.6.0.4
hybridbackend_tf115_cu114.libs/libkrb5-1301c0ea.so.3.3
hybridbackend_tf115_cu114.libs/libheimntlm-42521e96.so.0.1.0
hybridbackend_tf115_cu114-0.8.0.dev1679539959.dist-info/top_level.txt
hybridbackend_tf115_cu114-0.8.0.dev1679539959.dist-info/RECORD
hybridbackend_tf115_cu114-0.8.0.dev1679539959.dist-info/NOTICE
hybridbackend_tf115_cu114-0.8.0.dev1679539959.dist-info/LICENSE
hybridbackend_tf115_cu114-0.8.0.dev1679539959.dist-info/METADATA
hybridbackend_tf115_cu114-0.8.0.dev1679539959.dist-info/WHEEL
